ndx_depth_moseq/__init__.py
ndx_depth_moseq/spec/ndx-depth-moseq.extensions.yaml
ndx_depth_moseq/spec/ndx-depth-moseq.namespace.yaml
ndx_depth_moseq-0.1.2.dist-info/LICENSE.txt
ndx_depth_moseq-0.1.2.dist-info/METADATA
ndx_depth_moseq-0.1.2.dist-info/WHEEL
ndx_depth_moseq-0.1.2.dist-info/top_level.txt
ndx_depth_moseq-0.1.2.dist-info/RECORD
