Metadata-Version: 2.1
Name: ndx-depth-moseq
Version: 0.1.2
Summary: Extension for MoSeq-extract output
Home-page: 
Author: Paul Adkisson
Author-email: paul.wesley.adkisson@gmail.com
License: BSD-3
Keywords: NeurodataWithoutBorders,NWB,nwb-extension,ndx-extension
Classifier: Intended Audience :: Developers
Classifier: Intended Audience :: Science/Research
Classifier: License :: OSI Approved :: BSD License
License-File: LICENSE.txt
Requires-Dist: pynwb <3,>=1.5.0
Requires-Dist: hdmf <4,>=2.5.6
